README.md
setup.cfg
setup.py
commands/__init__.py
commands/_base.py
commands/both.py
commands/local.py
commands/remote.py
expl.egg-info/PKG-INFO
expl.egg-info/SOURCES.txt
expl.egg-info/dependency_links.txt
expl.egg-info/entry_points.txt
expl.egg-info/requires.txt
expl.egg-info/top_level.txt