Metadata-Version: 2.1
Name: expl
Version: 1.0.4
Summary: Generate exploit template
Home-page: https://github.com/AlirezaKm/expl
Author: Alireza Km
Author-email: alitm28@gmail.com
License: GPLv3
Keywords: exploit,template,generator
Platform: UNKNOWN
Classifier: Intended Audience :: Developers
Classifier: Topic :: Software Development :: Build Tools
Classifier: License :: OSI Approved :: GNU General Public License v3 (GPLv3)
Classifier: Programming Language :: Python :: 3
